SimpleNode/ActivationFunctions.py
SimpleNode/LabledData.py
SimpleNode/Layer.py
SimpleNode/NeuralNetwork.py
SimpleNode/__init__.py
SimpleNode-0.32.dist-info/LICENSE.txt
SimpleNode-0.32.dist-info/METADATA
SimpleNode-0.32.dist-info/WHEEL
SimpleNode-0.32.dist-info/top_level.txt
SimpleNode-0.32.dist-info/RECORD
